{
    "questions": [
      {
          "question": "Здравствуйте! Вы на странице опроса, задача которого состоит в изучении инфляционных ожиданий, потребительских настроений, а также уровня финансовой грамотности населения. Обратите внимание, что на некоторые вопросы может понадобиться калькулятор. Полученная от Вас информация – конфиденциальна. Все ответы – Ваши и других участников – будут учитываться только в обобщённом виде. Заполнение опроса займет около 20 минут.",
          "correct_answer": "без ответа"

      },
      {
        "question": "Сколько человек, включая Вас, проживает вместе с Вами в Вашей семье?",
        "answers": []
      },
      {
        "question": "Скажите, пожалуйста, как изменилось материальное положение Вашей семьи за последние 12 месяцев?",
        "answers": [
          "улучшилось",
          "осталось без изменений",
          "ухудшилось",
          "затрудняюсь ответить"
        ],
        "correct_answer": "затрудняюсь ответить"
      },
      {
        "question": "Как, по-вашему мнению, изменится материальное положение Вашей семьи в следующие 12 месяцев?",
        "answers": [
          "улучшится",
          "останется без изменений",
          "ухудшится",
          "затрудняюсь ответить"
        ],
        "correct_answer": "затрудняюсь ответить"
      },
      {
        "question": "Если говорить о крупных покупках для дома (таких как мебель, холодильник, бытовая электроника, телевизор), то какое сейчас, по Вашему мнению, время для того, чтобы делать такие покупки?",
        "answers": [
          "хорошее",
          "не хорошее, но и не плохое",
          "плохое",
          "затрудняюсь ответить"
        ],
        "correct_answer": "затрудняюсь ответить"
      },
      {
        "question": "Какое сейчас, по Вашему мнению, время для того, чтобы делать сбережения?",
        "answers": [
          "хорошее",
          "не хорошее, но и не плохое",
          "плохое",
          "затрудняюсь ответить"
        ],
        "correct_answer": "затрудняюсь ответить"
      },
      {
        "question": "Какие из перечисленных крупных расходов были у Вас (Вашей семьи) за последние три месяца?",
        "answers": [
          "траты на ремонт жилья, дома, дачи (капитальный или текущий)",
          "траты на отдых, поездки по России или за границу",
          "траты на образование (своё, детей)",
          "траты на крупные траты на лечение (своё, детей, родственников)",
          "траты на семейное торжество (юбилей, свадьба и т.п.)",
          "покупка дома, квартиры, дачи, садового участка",
          "покупка автомобиля",
          "покупка техники для дома (холодильник, морозильник, стиральная или посудомоечная машина, микроволновая печь, электро- или газовая плита, духовой шкаф и т.п.)",
          "покупка мебели",
          "покупка аудио-, видео-, фототехники (телевизор, dvd-проигрыватель, музыкальный центр, аудиосистема, видеокамера, фотоаппарат и т.п.)",
          "покупка компьютера, ноутбука, планшета, игровых приставок и т.п.",
          "покупка мобильного телефона, смартфона, коммуникатора, gps-навигатора",
          "другие крупные расходы",
          "никаких крупных расходов не было",
          "не знаю, затрудняюсь ответить"
        ],
        "correct_answer": ["траты на ремонт жилья, дома, дачи (капитальный или текущий)", "траты на семейное торжество (юбилей, свадьба и т.п.)"]
      },
      {
        "question": "Как часто за последние три месяца Вы видели, слышали или читали какую-либо информацию, сообщения или заявления, касающиеся деятельности Центрального банка РФ?",
        "answers": [
          "ни разу",
          "один-два раза",
          "три-четыре раза",
          "пять раз и более",
          "затрудняюсь ответить"
        ],
        "correct_answer": "затрудняюсь ответить"
      },
      {
        "question": "Какое из перечисленных на карточке описаний точнее всего соответствует материальному положению Вашей семьи?",
        "answers": [
          "денег не хватает даже на питание",
          "на питание денег хватает, но не хватает на покупку одежды и обуви",
          "на покупку одежды и обуви денег хватает, но не хватает на покупку крупной бытовой техники",
          "денег вполне хватает на покупку крупной бытовой техники, но мы не можем купить новую машину",
          "денег хватает на всё, кроме таких дорогих приобретений, как квартира, дом",
          "материальных затруднений не испытываем, при необходимости могли бы приобрести квартиру, дом"
        ],
        "correct_answer": "затрудняюсь ответить"
      },
      {
        "question": "По Вашему мнению, какая инфляция будет через 12 месяцев (в %):",
        "answers": [
          "менее 2%",
          "3-5%",
          "6-8%",
          "9-12%",
          "13-16%",
          "17-20%",
          "21-25%",
          "26-30%",
          "31-40%",
          "41-50%",
          "51% и более"
        ],
        "correct_answer": "затрудняюсь ответить"
      },
      {
        "question": "Как Вы думаете, что из перечисленного страхуется государственной системой страхования вкладов?",
        "answers": [
          "вклады от населения в финансовых организациях всех видов – банках, страховых компаниях, инвестиционных фондах и т.п.",
          "вклады в акции российских компаний",
          "паи в паевых инвестиционных фондах",
          "вклады в банках",
          "вложения в недвижимость в виде долевого участия",
          "ничего из перечисленного",
          "затрудняюсь ответить"
        ],
        "correct_answer": "затрудняюсь ответить"
      },
      {
        "question": "Какова максимальная сумма вклада в российском банке, которая полностью застрахована государством?",
        "answers": [
          "1 000 000 рублей",
          "1 200 000 рублей",
          "1 400 000 рублей",
          "1 500 000 рублей",
          "5 000 000 рублей",
          "9 990 000 рублей",
          "затрудняюсь ответить"
        ],
        "correct_answer": "затрудняюсь ответить"
      },
      {
        "question": "Скажите, пожалуйста, как Вы думаете, что такое ключевая ставка?",
        "answers": [
          "ставка Центрального банка",
          "ставка межбанковского рынка",
          "ставка кредита банков населению",
          "ставка вкладов населения в банках",
          "затрудняюсь ответить"
        ],
        "correct_answer": "затрудняюсь ответить"
      },
      {
        "question": "Предположим, что Вы положили 100 000 рублей на счет в банк на два года под 8% в год. Сколько денег будет на Вашем счете через 2 года, если Вы не будете снимать деньги со счета или пополнять свой счет?",
        "answers": [
          "более 108 000 рублей",
          "ровно 108 000 рублей",
          "менее 108 000 рублей",
          "затрудняюсь ответить"
        ],
        "correct_answer": "затрудняюсь ответить"
      },
      {
        "question": "Предположим, что Вы положили 100 000 рублей на счет в банк на пять лет под 10% в год. Проценты будут начисляться ежегодно и прибавляться к основной сумме вклада. Сколько денег будет на Вашем счете через 5 лет, если Вы не будете снимать с этого счета ни основную сумму, ни начисленные проценты?",
        "answers": [
          "более 150 000 рублей",
          "ровно 150 000 рублей",
          "менее 150 000 рублей",
          "затрудняюсь ответить"
        ],
        "correct_answer": "затрудняюсь ответить"
      },
      {
        "question": "Представьте себе, что год назад Вы положили деньги на счет со ставкой 8% в год, а уровень инфляции за год составил 10%. Как Вы думаете, сегодня на деньги, которые есть на Вашем счете, в среднем можно купить больше, меньше или столько же товаров и услуг, что и год назад?",
        "answers": [
          "больше, чем год назад",
          "ровно столько же",
          "меньше, чем год назад",
          "затрудняюсь ответить"
        ],
        "correct_answer": "затрудняюсь ответить"
      },
      {
        "question": "Предположим, что Вы увидели телевизор одной и той же модели на распродаже в двух разных магазинах. Первоначальная цена телевизора в одном магазине составляла 10000 рублей, а скидка составила 10% с первоначальной цены. В другом цену Вы не запомнили, но предлагалась скидка 15%, которая составила 1500 рублей. Что выгоднее - скидка в 10% или 1500 рублей?",
        "answers": [
          "скидка в 10%",
          "скидка в 1500 рублей",
          "различий между скидками нет",
          "затрудняюсь ответить"
        ],
        "correct_answer": "затрудняюсь ответить"
      },
      {
        "question": "По Вашему мнению, насколько можно ожидать, что цены в следующие 12 месяцев (год) снизятся? Оцените по 10-бальной шкале, где 0 – наименее вероятно, 10- наиболее вероятно.",
        "answers": [
          "затрудняюсь ответить",
          "0",
          "1",
          "2",
          "3",
          "4",
          "5",
          "6",
          "7",
          "8",
          "9",
          "10"
        ],
        "correct_answer": "затрудняюсь ответить"
      },
      {
        "question": "По Вашему мнению, насколько можно ожидать, что цены в следующие 12 месяцев (год) вырастут на 0-2%? Оцените по 10-бальной шкале, где 0 – наименее вероятно, 10- наиболее вероятно.",
        "answers": [
          "затрудняюсь ответить",
          "0",
          "1",
          "2",
          "3",
          "4",
          "5",
          "6",
          "7",
          "8",
          "9",
          "10"
        ],
        "correct_answer": "затрудняюсь ответить"
      },
      {
        "question": "По Вашему мнению, насколько можно ожидать, что цены в следующие 12 месяцев (год) вырастут на 3–5%? Оцените по 10-бальной шкале, где 0 – наименее вероятно, 10- наиболее вероятно.",
        "answers": [
          "затрудняюсь ответить",
          "0",
          "1",
          "2",
          "3",
          "4",
          "5",
          "6",
          "7",
          "8",
          "9",
          "10"
        ],
        "correct_answer": "затрудняюсь ответить"
      },
      {
        "question": "По Вашему мнению, насколько можно ожидать, что цены в следующие 12 месяцев (год) вырастут на 6–8%? Оцените по 10-бальной шкале, где 0 – наименее вероятно, 10- наиболее вероятно.",
        "answers": [
          "затрудняюсь ответить",
          "0",
          "1",
          "2",
          "3",
          "4",
          "5",
          "6",
          "7",
          "8",
          "9",
          "10"
        ],
        "correct_answer": "затрудняюсь ответить"
      },
      {
        "question": "По Вашему мнению, насколько можно ожидать, что цены в следующие 12 месяцев (год) вырастут на 9–12%? Оцените по 10-бальной шкале, где 0 – наименее вероятно, 10- наиболее вероятно.",
        "answers": [
          "затрудняюсь ответить",
          "0",
          "1",
          "2",
          "3",
          "4",
          "5",
          "6",
          "7",
          "8",
          "9",
          "10"
        ],
        "correct_answer": "затрудняюсь ответить"
      },
      {
        "question": "По Вашему мнению, насколько можно ожидать, что цены в следующие 12 месяцев (год) вырастут на 13–16%? Оцените по 10-бальной шкале, где 0 – наименее вероятно, 10- наиболее вероятно.",
        "answers": [
          "затрудняюсь ответить",
          "0",
          "1",
          "2",
          "3",
          "4",
          "5",
          "6",
          "7",
          "8",
          "9",
          "10"
        ],
        "correct_answer": "затрудняюсь ответить"
      },
      {
        "question": "По Вашему мнению, насколько можно ожидать, что цены в следующие 12 месяцев (год) вырастут на 17–20%? Оцените по 10-бальной шкале, где 0 – наименее вероятно, 10- наиболее вероятно.",
        "answers": [
          "затрудняюсь ответить",
          "0",
          "1",
          "2",
          "3",
          "4",
          "5",
          "6",
          "7",
          "8",
          "9",
          "10"
        ],
        "correct_answer": "затрудняюсь ответить"
      },
      {
        "question": "По Вашему мнению, насколько можно ожидать, что цены в следующие 12 месяцев (год) вырастут на 21–25%? Оцените по 10-бальной шкале, где 0 – наименее вероятно, 10- наиболее вероятно.",
        "answers": [
          "затрудняюсь ответить",
          "0",
          "1",
          "2",
          "3",
          "4",
          "5",
          "6",
          "7",
          "8",
          "9",
          "10"
        ],
        "correct_answer": "затрудняюсь ответить"
      },
      {
        "question": "По Вашему мнению, насколько можно ожидать, что цены в следующие 12 месяцев (год) вырастут на 26–30%? Оцените по 10-бальной шкале, где 0 – наименее вероятно, 10- наиболее вероятно.",
        "answers": [
          "затрудняюсь ответить",
          "0",
          "1",
          "2",
          "3",
          "4",
          "5",
          "6",
          "7",
          "8",
          "9",
          "10"
        ],
        "correct_answer": "затрудняюсь ответить"
      },
      {
        "question": "По Вашему мнению, насколько можно ожидать, что цены в следующие 12 месяцев (год) вырастут на 31–40%? Оцените по 10-бальной шкале, где 0 – наименее вероятно, 10- наиболее вероятно.",
        "answers": [
          "затрудняюсь ответить",
          "0",
          "1",
          "2",
          "3",
          "4",
          "5",
          "6",
          "7",
          "8",
          "9",
          "10"
        ],
        "correct_answer": "затрудняюсь ответить"
      },
      {
        "question": "По Вашему мнению, насколько можно ожидать, что цены в следующие 12 месяцев (год) вырастут на 41–50%? Оцените по 10-бальной шкале, где 0 – наименее вероятно, 10- наиболее вероятно.",
        "answers": [
          "затрудняюсь ответить",
          "0",
          "1",
          "2",
          "3",
          "4",
          "5",
          "6",
          "7",
          "8",
          "9",
          "10"
        ],
        "correct_answer": "затрудняюсь ответить"
      },
      {
        "question": "По Вашему мнению, насколько можно ожидать, что цены в следующие 12 месяцев (год) вырастут на 51% и более? Оцените по 10-бальной шкале, где 0 – наименее вероятно, 10- наиболее вероятно.",
        "answers": [
          "затрудняюсь ответить",
          "0",
          "1",
          "2",
          "3",
          "4",
          "5",
          "6",
          "7",
          "8",
          "9",
          "10"
        ],
        "correct_answer": "затрудняюсь ответить"
      },
      {
        "question": "Оцените, насколько Вы уверены в ответах, которые дали в вопросах об изменениях цен в следующие 12 месяцев? Оцените по 10-бальной шкале, где 0 – совсем не уверен, 10- полностью уверен.",
        "answers": [
          "0",
          "1",
          "2",
          "3",
          "4",
          "5",
          "6",
          "7",
          "8",
          "9",
          "10"
        ],
        "correct_answer": "затрудняюсь ответить"
      }
    ]
}